gnlib/__init__.py
gnlib/gnlib.py
gnlib-0.0.1.dist-info/METADATA
gnlib-0.0.1.dist-info/WHEEL
gnlib-0.0.1.dist-info/top_level.txt
gnlib-0.0.1.dist-info/RECORD
